tmexio/__init__.py
tmexio/documentation.py
tmexio/event_handlers.py
tmexio/exceptions.py
tmexio/handler_builders.py
tmexio/main.py
tmexio/markers.py
tmexio/packagers.py
tmexio/py.typed
tmexio/server.py
tmexio/specs.py
tmexio/structures.py
tmexio/types.py
tmexio-0.2.1.dist-info/METADATA
tmexio-0.2.1.dist-info/WHEEL
tmexio-0.2.1.dist-info/RECORD
